{"urls":[
{"name":"👑果冻自用👑","url":"https://github.com/laozi4vip/myysjk/raw/main/jelly.json"},  
{"name":"🐦鸟叔&👑果冻👑","url":"https://github.com/laozi4vip/JellyZYC/raw/main/niaoshu/tongyong.json"},   
{"name":"🍚饭太硬&👑果冻👑","url":"http://www.饭太硬.net/tv"},    #http://fan.888484.xyz/tv#http://fan.xxooo.cf/tv
{"name":"🐂放牛娃&👑果冻👑","url":"http://tvbox.xn--4kq62z5rby2qupq9ub.top/"}, 
{"name":"🤵jack老师&👑果冻👑","url":"http://ok321.top/tv"},
{"name":"💯真心&👑果冻👑","url":"http://www.fish2018.ip-ddns.com/p/jsm.json"},   #http://www.fish2018.ip-ddns.com/z/FongMi.json
{"name":"⭕️OK炸天&👑果冻👑","url":"http://ok321.top/tv"},
{"name":"☃️讴歌&👑果冻👑","url":"http://tv.nxog.top/m/"}, 
#{"name":"👿刺猬&👑果冻👑","url":"https://www.xn--rgv465a.top/刺猬线路禁止贩卖"},
#{"name":"☁️云星&👑果冻👑","url":"http://itvbox.cc/云星日记"},
{"name":"🦉金鹰&👑果冻👑","url":"http://530.my3v.work/jy.json"},  
{"name":"🥣小米&👑果冻👑","url":"https://mpanso.me/DEMO.json"},
{"name":"😹吃猫的鱼&👑果冻👑","url":"https://d.kstore.dev/download/7213/吃猫的鱼"},
{"name":"🐼肥猫&👑果冻👑","url":"http://肥猫.live"},
{"name":"🦆小白&👑果冻👑","url":"http://bp.tvbox.cam/"},
#{"name":"🐟摸鱼&👑果冻👑","url":"http://我不是.摸鱼儿.top"},
{"name":"💠刘备&👑果冻👑","url":"https://raw.liucn.cc/box/m.json"},  
#{"name":"☯️道长&👑果冻👑","url":"https://pastebin.com/raw/5NHaxyGR"},    
{"name":"🍡PG&👑果冻👑","url":"https://mirror.ghproxy.com/raw.githubusercontent.com/gaotianliuyun/gao/master/0825.json"},
#{"name":"🏆荷城&👑果冻👑","url":"http://rihou.vip:99/荷城茶秀"},
#{"name":"🌟日后&👑果冻👑","url":"http://rihou.cc:66"},
{"name":"🚒运输&👑果冻👑","url":"https://weixine.net/ysc.json"},
{"name":"🚒不好打开运输&👑果冻👑","url":"https://weixine.net/ysc.json"},
{"name":"💞骚零&👑果冻👑","url":"https://100km.top/0"},
{"name":"💝恋影&👑果冻👑","url":"https://www.lianyingtv.com/fast/fast"},
{"name":"🌼菜妮丝&👑果冻👑","url":"https://tv.xn--yhqu5zs87a.top"},
{"name":"🍀俊宇&👑果冻👑","url":"http://home.jundie.top:81/top98.json"},
{"name":"💦巧技&👑果冻👑","url":"http://cdn.qiaoji8.com/tvbox.json"},
{"name":"📿神器&👑果冻👑","url":"http://home.jundie.top:81/top98.json"},
{"name":"🌪南风&👑果冻👑","url":"https://ghproxy.net/https://raw.githubusercontent.com/yoursmile66/TVBox/main/XC.json"}
]}
#☯️🌈🏳️‍🌈⚡️👒🥦🌤️🌙💦🌊🌅🌞🌟🎯🍭🎀🐚💍💎💠🏠🏘🎒🏩🎪📮📺🛰🍫🎭🔰🍷🥣🎆🎇🚥🛀🏻🔱🥐🏮🎁🚀🎧📌⛽️📔📕⏰
#🐼🐦🐜🐈‍⬛🦓🦒🐙🐟🐳🐬👼😹🐱🦊🐺🐯🦁☃️🐝🐁🐭🐹🙈🦆🐸🦞🎏🐳👿🦉🐴🐂🐊🐥🐢🐲️🐉🐍🐷🐾🐔🐝
#🎉🎊💐🌹🌼💮🏵️🏵🌸🌺🌾🍃🌴🌿🌕🌽🍌🥑🍉🎃🍆🥝🥭🍐🍊🍇🍈🍑🍓🍅🍎🥥🌮🍔🌭🍩🍣🍫🍡🍵🍳
#🏄🏻🤵👮🕵🧛‍♂️🎎👬🙇🏂🏋🏻🚴🏻💃👀👽🗽🧞
#🎹⭕️🍧🍟🔥☔️🌰🛠📿🏆🧲🔋🅱️🆎🆕Ⓜ️⏮️🔃♻📀🚁🚑🚒🚌⛵️🚢🚄🛸🚊🔮💄🛎🎸🎬🎦👉🈚🏔🎱📽️🏀⚽🎵🎼🎶🎤🚧🔎🏷️💰📡👊📛🧶
#❤️🧡💙❤💜💛💚💖💓💕💯
